{"ice":{"offense":{"two":["flying","ground","grass","dragon"],"half":["steel","fire","water","ice"],"none":[]},"defense":{"two":["fighting","rock","steel","fire"],"half":["ice"],"none":[]},"languages":{"en":"Ice","ko":"얼음","de":"Eis","fr":"Glace","es":"Hielo","ja":"こおり"}},"grass":{"offense":{"two":["ground","rock","water"],"half":["flying","poison","bug","steel","fire","grass","dragon"],"none":[]},"defense":{"two":["flying","poison","bug","fire","ice"],"half":["ground","water","grass","electric"],"none":[]},"languages":{"en":"Grass","ko":"풀","de":"Pflanze","fr":"Plante","es":"Planta","ja":"くさ"}},"dark":{"offense":{"two":["ghost","psychic"],"half":["fighting","dark","fairy"],"none":[]},"defense":{"two":["fighting","bug","fairy"],"half":["ghost","dark"],"none":["psychic"]},"languages":{"en":"Dark","ko":"악","de":"Unlicht","fr":"Ténèbres","es":"Siniestro","ja":"あく"}},"bug":{"offense":{"two":["grass","psychic","dark"],"half":["fighting","flying","poison","ghost","steel","fire","fairy"],"none":[]},"defense":{"two":["flying","rock","fire"],"half":["fighting","ground","grass"],"none":[]},"languages":{"en":"Bug","ko":"벌레","de":"Käfer","fr":"Insecte","es":"Bicho","ja":"むし"}},"fairy":{"offense":{"two":["fighting","dragon","dark"],"half":["poison","steel","fire"],"none":[]},"defense":{"two":["poison","steel"],"half":["fighting","bug","dark"],"none":["dragon"]},"languages":{"en":"Fairy","ko":"페어리","de":"Fee","fr":"Fée","es":"Hada","ja":"フェアリー"}},"water":{"offense":{"two":["ground","rock","fire"],"half":["water","grass","dragon"],"none":[]},"defense":{"two":["grass","electric"],"half":["steel","fire","water","ice"],"none":[]},"languages":{"en":"Water","ko":"물","de":"Wasser","fr":"Eau","es":"Agua","ja":"みず"}},"electric":{"offense":{"two":["flying","water"],"half":["grass","electric","dragon"],"none":["ground"]},"defense":{"two":["ground"],"half":["flying","steel","electric"],"none":[]},"languages":{"en":"Electric","ko":"전기","de":"Elektro","fr":"Électrik","es":"Eléctrico","ja":"でんき"}},"normal":{"offense":{"two":[],"half":["rock","steel"],"none":["ghost"]},"defense":{"two":["fighting"],"half":[],"none":["ghost"]},"languages":{"en":"Normal","ko":"노말","de":"Normal","fr":"Normal","es":"Normal","ja":"ノーマル"}},"dragon":{"offense":{"two":["dragon"],"half":["steel"],"none":["fairy"]},"defense":{"two":["ice","dragon","fairy"],"half":["fire","water","grass","electric"],"none":[]},"languages":{"en":"Dragon","ko":"드래곤","de":"Drache","fr":"Dragon","es":"Dragón","ja":"ドラゴン"}},"psychic":{"offense":{"two":["fighting","poison"],"half":["steel","psychic"],"none":["dark"]},"defense":{"two":["bug","ghost","dark"],"half":["fighting","psychic"],"none":[]},"languages":{"en":"Psychic","ko":"에스퍼","de":"Psycho","fr":"Psy","es":"Psíquico","ja":"エスパー"}},"poison":{"offense":{"two":["grass","fairy"],"half":["poison","ground","rock","ghost"],"none":["steel"]},"defense":{"two":["ground","psychic"],"half":["fighting","poison","bug","grass","fairy"],"none":[]},"languages":{"en":"Poison","ko":"독","de":"Gift","fr":"Poison","es":"Veneno","ja":"どく"}},"ghost":{"offense":{"two":["ghost","psychic"],"half":["dark"],"none":["normal"]},"defense":{"two":["ghost","dark"],"half":["poison","bug"],"none":["normal","fighting"]},"languages":{"en":"Ghost","ko":"고스트","de":"Geist","fr":"Spectre","es":"Fantasma","ja":"ゴースト"}},"flying":{"offense":{"two":["fighting","bug","grass"],"half":["rock","steel","electric"],"none":[]},"defense":{"two":["rock","electric","ice"],"half":["fighting","bug","grass"],"none":["ground"]},"languages":{"en":"Flying","ko":"비행","de":"Flug","fr":"Vol","es":"Volador","ja":"ひこう"}},"rock":{"offense":{"two":["flying","bug","fire","ice"],"half":["fighting","ground","steel"],"none":[]},"defense":{"two":["fighting","ground","steel","water","grass"],"half":["normal","flying","poison","fire"],"none":[]},"languages":{"en":"Rock","ko":"바위","de":"Gestein","fr":"Roche","es":"Roca","ja":"いわ"}},"steel":{"offense":{"two":["rock","ice","fairy"],"half":["steel","fire","water","electric"],"none":[]},"defense":{"two":["fighting","ground","fire"],"half":["normal","flying","rock","bug","steel","grass","psychic","ice","dragon","fairy"],"none":["poison"]},"languages":{"en":"Steel","ko":"강철","de":"Stahl","fr":"Acier","es":"Acero","ja":"はがね"}},"ground":{"offense":{"two":["poison","rock","steel","fire","electric"],"half":["bug","grass"],"none":["flying"]},"defense":{"two":["water","grass","ice"],"half":["poison","rock"],"none":["electric"]},"languages":{"en":"Ground","ko":"땅","de":"Boden","fr":"Sol","es":"Tierra","ja":"じめん"}},"fire":{"offense":{"two":["bug","steel","grass","ice"],"half":["rock","fire","water","dragon"],"none":[]},"defense":{"two":["ground","rock","water"],"half":["bug","steel","fire","grass","ice","fairy"],"none":[]},"languages":{"en":"Fire","ko":"불꽃","de":"Feuer","fr":"Feu","es":"Fuego","ja":"ほのお"}},"fighting":{"offense":{"two":["normal","rock","steel","ice","dark"],"half":["flying","poison","bug","psychic","fairy"],"none":["ghost"]},"defense":{"two":["flying","psychic","fairy"],"half":["rock","bug","dark"],"none":[]},"languages":{"en":"Fighting","ko":"격투","de":"Kampf","fr":"Combat","es":"Lucha","ja":"かくとう"}}}